gcr_chat/__init__.py
gcr_chat/chatbot/__init__.py
gcr_chat/chatbot/client.py
gcr_chat/chatbot/command.py
gcr_chat/chatbot/exceptions.py
gcr_chat/models.py
gcr_chat-0.1.3.dist-info/METADATA
gcr_chat-0.1.3.dist-info/WHEEL
gcr_chat-0.1.3.dist-info/RECORD
