Metadata-Version: 2.1
Name: gcr_chat
Version: 0.1.3
Summary: Chatbot command parsing library to be used in conjunction with Google Cloud Run and GSuite Chat.
Author: Sam Kenney
Author-email: sam.kenney@me.com
Requires-Python: >=3.11,<4.0
Classifier: Programming Language :: Python :: 3
Classifier: Programming Language :: Python :: 3.11
Requires-Dist: pydantic (>=2,<3)
